upbit/__init__.py
upbit/authentication.py
upbit/client.py
upbit/models.py
upbit/pkginfo.py
upbit/utils.py
upbit/websocket.py
upbit_client-1.3.4.1.dist-info/LICENSE
upbit_client-1.3.4.1.dist-info/METADATA
upbit_client-1.3.4.1.dist-info/WHEEL
upbit_client-1.3.4.1.dist-info/top_level.txt
upbit_client-1.3.4.1.dist-info/RECORD
