Metadata-Version: 2.1
Name: upbit-client
Version: 1.3.4.1
Summary: Upbit OPEN API Client
Home-page: https://github.com/uJhin/upbit-client
Download-URL: https://github.com/uJhin/upbit-client/releases
Author: ujhin
Author-email: ujhin942@gmail.com
License: MIT License
Keywords: Upbit,upbit,upbit-client,Upbit-Client,Upbit_client,Upbit-api-connector,upbit-api-connector,Upbit_api_connector,upbit_api_connector
Classifier: Programming Language :: Python :: 3.8
Classifier: Programming Language :: Python :: 3.9
Classifier: Programming Language :: Python :: 3.10
Classifier: Programming Language :: Python :: 3.11
Classifier: Programming Language :: Python :: 3.12
Requires-Python: >=3.8
Provides-Extra: fido
License-File: LICENSE
